probabilistic/__init__.py
probabilistic/core.py
probabilistic.py-0.2.0.dist-info/METADATA
probabilistic.py-0.2.0.dist-info/WHEEL
probabilistic.py-0.2.0.dist-info/top_level.txt
probabilistic.py-0.2.0.dist-info/RECORD
