Metadata-Version: 2.1
Name: probabilistic.py
Version: 0.2.0
Summary: A package for probabilistic function execution.
Home-page: https://github.com/r-kataria/probabilistic.py
Author: R Kataria
Classifier: Programming Language :: Python :: 3
